pyade/__init__.py
pyade/commons.py
pyade/de.py
pyade/ilshade.py
pyade/jade.py
pyade/jso.py
pyade/lshade.py
pyade/lshadecnepsin.py
pyade/mmts.py
pyade/mpede.py
pyade/sade.py
pyade/saepsdemmts.py
pyade/shade.py
pyade_python-1.1.dist-info/LICENSE
pyade_python-1.1.dist-info/METADATA
pyade_python-1.1.dist-info/WHEEL
pyade_python-1.1.dist-info/top_level.txt
pyade_python-1.1.dist-info/RECORD
