Metadata-Version: 2.1
Name: pyade-python
Version: 1.1
Summary: A Python Advanced Differential Evolution algorithms library
Home-page: https://github.com/xKuZz/pyade
Author: xKuZz
Author-email: davidcr96@gmail.com
License: MIT
Platform: UNKNOWN
